txtra/__init__.py
txtra/__main__.py
txtra/provider/activegate-ss.yml
txtra/provider/adobe-sign.yml
txtra/provider/adobe.yml
txtra/provider/akamai-cloudpiercer.yml
txtra/provider/alibaba-cloud.yml
txtra/provider/android-mdm.yml
txtra/provider/anodot.yml
txtra/provider/apple.yml
txtra/provider/atlassian.yml
txtra/provider/aws-ses.yml
txtra/provider/azure.yml
txtra/provider/barracuda-bvm.yml
txtra/provider/blitz.yml
txtra/provider/botify.yml
txtra/provider/brave.yml
txtra/provider/bugcrowd.yml
txtra/provider/citrix.yml
txtra/provider/cloudcontrol.yml
txtra/provider/dailymotion.yml
txtra/provider/detectify.yml
txtra/provider/docusign.yml
txtra/provider/dropbox.yml
txtra/provider/dynatrace.yml
txtra/provider/facebook.yml
txtra/provider/firebase.yml
txtra/provider/globalsign.yml
txtra/provider/gmail.yml
txtra/provider/godaddy.yml
txtra/provider/haveibeenpwned.yml
txtra/provider/heroku.yml
txtra/provider/knowbe4.yml
txtra/provider/letsencrypt.yml
txtra/provider/line-works.yml
txtra/provider/loaderio.yml
txtra/provider/logmein.yml
txtra/provider/mailigen.yml
txtra/provider/mailjet.yml
txtra/provider/mailru.yml
txtra/provider/o365.yml
txtra/provider/pardot.yml
txtra/provider/postman.yml
txtra/provider/protonmail.yml
txtra/provider/segment.yml
txtra/provider/sendgrid.yml
txtra/provider/sendinblue.yml
txtra/provider/site24x7.yml
txtra/provider/sophos.yml
txtra/provider/spycloud.yml
txtra/provider/statuspage.yml
txtra/provider/swisssign.yml
txtra/provider/symantec-mdm.yml
txtra/provider/t-systems.yml
txtra/provider/teamviewer.yml
txtra/provider/tinfosecurity.yml
txtra/provider/tmes.yml
txtra/provider/twilio.yml
txtra/provider/webaccel.yml
txtra/provider/webex.yml
txtra/provider/wmail.yml
txtra/provider/workplace.yml
txtra/provider/wrike.yml
txtra/provider/yandex.yml
txtra/provider/zapier.yml
txtra/provider/zoho.yml
txtra/provider/zoom.yml
txtra-0.1.2.dist-info/licenses/LICENSE
txtra-0.1.2.dist-info/METADATA
txtra-0.1.2.dist-info/WHEEL
txtra-0.1.2.dist-info/entry_points.txt
txtra-0.1.2.dist-info/top_level.txt
txtra-0.1.2.dist-info/RECORD
