Metadata-Version: 2.4
Name: txtra
Version: 0.1.2
Summary: txtra(txt record analyzer) is a tool that profiles the cloud services used by an organization using the txt records returned by name resolution for the domain in question.
Author: wild0ni0n
Project-URL: Homepage, https://github.com/wild0ni0n/txtra
Project-URL: Bug Tracker, https://github.com/wild0ni0n/txtra/issues
Classifier: Programming Language :: Python :: 3
Classifier: License :: OSI Approved :: MIT License
Requires-Python: >=3.12
License-File: LICENSE
Requires-Dist: colorama==0.4.6
Requires-Dist: dnspython==2.7.0
Requires-Dist: PyYAML==6.0.1
Requires-Dist: tldextract==5.3.0
Dynamic: license-file
